rote_satio/__init__.py
rote_satio/models/__init__.py
rote_satio/models/classification/__init__.py
rote_satio/models/segmentatition/__init__.py
rote_satio/models/segmentatition/auto_segmentation.py
rote_satio/models/segmentatition/planet/__init__.py
rote_satio/models/segmentatition/planet/clustering_pipeline.joblib
rote_satio/models/segmentatition/planet/dispatcher.py
rote_satio/models/segmentatition/planet/preprocessing_pipeline.joblib
rote_satio/models/train_model.py
rote_satio/models/utils/__init__.py
rote_satio/models/utils/utils.py
rote_satio/utils/__init__.py
rote_satio/utils/base_transformer.py
rote_satio/utils/geobia_transformer.py
rote_satio/utils/index_transformer.py
rote_satio/utils/spydex_scraper.py
rote_satio/utils/utils.py
rote_satio-0.0.21b0.dist-info/LICENSE
rote_satio-0.0.21b0.dist-info/METADATA
rote_satio-0.0.21b0.dist-info/WHEEL
rote_satio-0.0.21b0.dist-info/RECORD
