Metadata-Version: 2.1
Name: rote_satio
Version: 0.0.21b0
Summary: A package with utils for ml for remote sensing
License: MIT
Author: Hector Patino
Requires-Python: >=3.10,<4.0
Classifier: License :: OSI Approved :: MIT License
Classifier: Programming Language :: Python :: 3
Classifier: Programming Language :: Python :: 3.10
Classifier: Programming Language :: Python :: 3.11
Classifier: Programming Language :: Python :: 3.12
Requires-Dist: dask[dataframe] (==2024.5.1)
Requires-Dist: feature-engine (==1.7.0)
Requires-Dist: kneed (>=0.8.5,<0.9.0)
Requires-Dist: rioxarray (==0.15.5)
Requires-Dist: scikit-image (==0.23.2)
Requires-Dist: scikit-learn (>=1.5.0,<2.0.0)
Requires-Dist: spyndex (==0.6.0)
Requires-Dist: typer (==0.12.3)
Requires-Dist: umap-learn (==0.5.6)
